{
  "users": [
    {
      "id": 1,
      "name": "laoma1",
      "phone": "13976456754444",
      "address": "北京"
    },
    {
      "id": 2,
      "name": "laoma",
      "phone": 13976456754,
      "address": "北京"
    },
    {
      "id": 3,
      "name": "laoma",
      "phone": 13976456754,
      "address": "北京"
    },
    {
      "id": 4,
      "name": "laoma",
      "phone": 13976456754,
      "address": "北京"
    },
    {
      "id": 5,
      "name": "laoma",
      "phone": 13976456754,
      "address": "北京"
    },
    {
      "id": 6,
      "name": "laoma",
      "phone": 13976456754,
      "address": "北京"
    },
    {
      "name": "laoma777",
      "phone": "777",
      "address": "xihu",
      "id": 1551081943903
    }
  ]
}